<?xml version="1.0" encoding="UTF-8" standalone="yes"?>
<!--IATI Publications - UNDP Development Projects by Countries-->
<iati-activities xmlns:xsi="http://www.w3.org/2001/XMLSchema-instance" xmlns:xsd="http://www.w3.org/2001/XMLSchema" generated-datetime="2016-02-08T15:21:38" version="1.04">
  <!--Swaziland-->
  <iati-activity last-updated-datetime="2016-02-01T00:00:00" default-currency="USD" xml:lang="en" hierarchy="1">
    <reporting-org ref="XM-DAC-41114" type="40">United Nations Development Programme</reporting-org>
    <iati-identifier>XM-DAC-41114-PROJECT-00061307</iati-identifier>
    <activity-status code="2">Implementation</activity-status>
    <related-activity type="2" ref="XM-DAC-41114-OUTPUT-00077632" />
    <title>Strengthening National Capacities for Poverty Reduction</title>
    <description type="1">To support the development of evidence policy development, capacity development for data generation, women economic empowernment through promotion of entreprenuership and sustainable business management.</description>
    <participating-org role="Implementing" type="10" ref="02897">National Execution</participating-org>
    <participating-org role="Accountable" type="10" ref="00012">United Nations Development Programme</participating-org>
    <participating-org role="Funding" type="40" ref="00012">UNITED NATIONS DEVELOPMENT PROGRAMME</participating-org>
    <participating-org role="Funding" type="10" ref="00230">GOVERNMENT OF SWAZILAND</participating-org>
    <activity-date type="start-planned" iso-date="2011-01-01">2011-01-01</activity-date>
    <activity-date type="start-actual" iso-date="2011-01-01">2011-01-01</activity-date>
    <activity-date type="end-planned" iso-date="2020-12-31">2020-12-31</activity-date>
    <recipient-country code="SZ">Swaziland</recipient-country>
    <contact-info>
      <email>registry.sz@undp.org</email>
    </contact-info>
    <activity-website>http://www.sz.undp.org/</activity-website>
    <default-flow-type code="10">ODA</default-flow-type>
    <default-aid-type code="C01">Project Type Interventions</default-aid-type>
    <collaboration-type code="4">Multilateral outflows</collaboration-type>
    <default-finance-type code="110">Grant</default-finance-type>
    <default-tied-status code="5">Untied</default-tied-status>
    <conditions attached="0" />
    <document-link format="application/msword" url="https://info.undp.org/docs/pdc/Documents/SWZ/Annual%20Project%20Report%20Poverty.doc">
      <title>Annual Project Report (APR)</title>
      <language code="en" />
      <category code="A08" />
    </document-link>
    <document-link format="application/msword" url="https://info.undp.org/docs/pdc/Documents/SWZ/Mid%20Term%20Final%20Evaluation%20Report%205-%20Outcome%20Poverty%20Reduction%20Programme%20Evaluation.docx">
      <title>Mid Term Evaluation Report -  THe Poverty Reduction PRogramme</title>
      <language code="en" />
      <category code="A07" />
    </document-link>
    <document-link format="application/pdf" url="https://info.undp.org/docs/pdc/Documents/SWZ/Project%20document%20for%20BWFS.pdf">
      <title>Project document for BWFS</title>
      <language code="en" />
      <category code="A01" />
      <category code="A02" />
      <category code="A03" />
      <category code="A04" />
      <category code="A05" />
      <category code="A08" />
    </document-link>
    <document-link format="application/pdf" url="http://open.undp.org/#project/00061307">
      <title>Purchase Order Summary</title>
      <language code="en" />
      <category code="A11" />
    </document-link>
    <document-link format="application/pdf" url="http://www.sz.undp.org/content/dam/swaziland/docs/documents/UNDP_SZ_Country_Programme_Action_Plan_2011_2015.pdf">
      <title>UNDP_SZ_Country_Programme_Action_Plan_2011_2015</title>
      <language code="en" />
      <category code="A09" />
    </document-link>
    <document-link format="text/html" url="http://procurement-notices.undp.org/index.cfm">
      <title>Request for Procurement</title>
      <language code="en" />
      <category code="A10" />
    </document-link>
  </iati-activity>
  <iati-activity last-updated-datetime="2016-02-01T00:00:00" default-currency="USD" xml:lang="en" hierarchy="2">
    <reporting-org ref="XM-DAC-41114" type="40">United Nations Development Programme</reporting-org>
    <iati-identifier>XM-DAC-41114-OUTPUT-00077632</iati-identifier>
    <related-activity type="1" ref="XM-DAC-41114-PROJECT-00061307" />
    <recipient-country code="SZ">Swaziland</recipient-country>
    <title xml:lang="en">Strength. Nat. Cap. Poverty</title>
    <description xml:lang="en" type="1">Development of national frameworks including policies, systems and processes that promote the access and effective utilization of productive resources by the poor is key in the project implemntation.</description>
    <activity-date type="start-planned" iso-date="2011-01-01">2011-01-01</activity-date>
    <activity-date type="start-actual" iso-date="2011-01-01">2011-01-01</activity-date>
    <activity-date type="end-planned" iso-date="2015-12-31">2015-12-31</activity-date>
    <sector code="15110" vocabulary="DAC" />
    <sector code="1" vocabulary="RO">Inclusive &amp; Sustainable Growth</sector>
    <country-budget-items vocabulary="1">
      <budget-item code="3.1.1" percentage="100">policy, planning and administration</budget-item>
    </country-budget-items>
    <participating-org role="Funding" type="10" ref="00230">GOVERNMENT OF SWAZILAND</participating-org>
    <participating-org role="Funding" type="40" ref="00012">UNITED NATIONS DEVELOPMENT PROGRAMME</participating-org>
    <budget type="2">
      <period-start iso-date="2016-01-01" />
      <period-end iso-date="2016-12-31" />
      <value currency="USD" value-date="2016-01-31">861151.000</value>
    </budget>
    <budget type="2">
      <period-start iso-date="2015-01-01" />
      <period-end iso-date="2015-12-31" />
      <value currency="USD" value-date="2015-12-31">382065.000</value>
    </budget>
    <budget type="2">
      <period-start iso-date="2014-01-01" />
      <period-end iso-date="2014-12-31" />
      <value currency="USD" value-date="2014-12-31">412870.000</value>
    </budget>
    <budget type="2">
      <period-start iso-date="2013-01-01" />
      <period-end iso-date="2013-12-31" />
      <value currency="USD" value-date="2013-12-31">739222.000</value>
    </budget>
    <budget type="2">
      <period-start iso-date="2012-01-01" />
      <period-end iso-date="2012-12-31" />
      <value currency="USD" value-date="2012-12-31">747435.000</value>
    </budget>
    <transaction>
      <transaction-type code="E">Expenditure</transaction-type>
      <value currency="USD" value-date="2016-01-31">625.000</value>
      <transaction-date iso-date="2016-01-31" />
      <provider-org ref="41114">United Nations development Programme</provider-org>
      <disbursement-channel code="2">Money is disbursed directly to the implementing institution and managed through a separate bank account</disbursement-channel>
    </transaction>
    <transaction>
      <transaction-type code="C">Commitment</transaction-type>
      <value currency="USD" value-date="2016-01-31">230988.000</value>
      <transaction-date iso-date="2016-01-31" />
      <provider-org ref="00230">GOVERNMENT OF SWAZILAND</provider-org>
      <receiver-org ref="41114">United Nations development Programme</receiver-org>
      <disbursement-channel code="2">Money is disbursed directly to the implementing institution and managed through a separate bank account</disbursement-channel>
    </transaction>
    <transaction>
      <transaction-type code="IF">Incoming funds</transaction-type>
      <value currency="USD" value-date="2016-01-31">0.000</value>
      <transaction-date iso-date="2016-01-31" />
      <provider-org ref="00230">GOVERNMENT OF SWAZILAND</provider-org>
      <receiver-org ref="41114">United Nations development Programme</receiver-org>
      <disbursement-channel code="2">Money is disbursed directly to the implementing institution and managed through a separate bank account</disbursement-channel>
    </transaction>
    <transaction>
      <transaction-type code="C">Commitment</transaction-type>
      <value currency="USD" value-date="2016-01-31">630163.000</value>
      <transaction-date iso-date="2016-01-31" />
      <provider-org ref="00012">UNITED NATIONS DEVELOPMENT PROGRAMME</provider-org>
      <receiver-org ref="41114">United Nations development Programme</receiver-org>
      <disbursement-channel code="2">Money is disbursed directly to the implementing institution and managed through a separate bank account</disbursement-channel>
    </transaction>
    <transaction>
      <transaction-type code="IF">Incoming funds</transaction-type>
      <value currency="USD" value-date="2016-01-31">0.000</value>
      <transaction-date iso-date="2016-01-31" />
      <provider-org ref="00012">UNITED NATIONS DEVELOPMENT PROGRAMME</provider-org>
      <receiver-org ref="41114">United Nations development Programme</receiver-org>
      <disbursement-channel code="2">Money is disbursed directly to the implementing institution and managed through a separate bank account</disbursement-channel>
    </transaction>
    <transaction>
      <transaction-type code="E">Expenditure</transaction-type>
      <value currency="USD" value-date="2015-12-31">383841.000</value>
      <transaction-date iso-date="2015-12-31" />
      <provider-org ref="41114">United Nations development Programme</provider-org>
      <disbursement-channel code="2">Money is disbursed directly to the implementing institution and managed through a separate bank account</disbursement-channel>
    </transaction>
    <transaction>
      <transaction-type code="E">Expenditure</transaction-type>
      <value currency="USD" value-date="2014-12-31">409070.000</value>
      <transaction-date iso-date="2014-12-31" />
      <provider-org ref="41114">United Nations development Programme</provider-org>
      <disbursement-channel code="2">Money is disbursed directly to the implementing institution and managed through a separate bank account</disbursement-channel>
    </transaction>
    <transaction>
      <transaction-type code="E">Expenditure</transaction-type>
      <value currency="USD" value-date="2013-12-31">738577.000</value>
      <transaction-date iso-date="2013-12-31" />
      <provider-org ref="41114">United Nations development Programme</provider-org>
      <disbursement-channel code="2">Money is disbursed directly to the implementing institution and managed through a separate bank account</disbursement-channel>
    </transaction>
    <transaction>
      <transaction-type code="E">Expenditure</transaction-type>
      <value currency="USD" value-date="2012-12-31">736188.000</value>
      <transaction-date iso-date="2012-12-31" />
      <provider-org ref="41114">United Nations development Programme</provider-org>
      <disbursement-channel code="2">Money is disbursed directly to the implementing institution and managed through a separate bank account</disbursement-channel>
    </transaction>
    <policy-marker code="1" vocabulary="DAC" significance="0">Gender Equality</policy-marker>
    <location ref="SZ">
      <location-id vocabulary="G1" code="934985" />
      <name>Mbabane</name>
      <description>capital of a political entity</description>
      <activity-description></activity-description>
      <administrative level="1" code="934985" vocabulary="G1" />
      <point srsName="http://www.opengis.net/def/crs/EPSG/0/4326">
        <pos>-26.316670 31.133330</pos>
      </point>
      <exactness code="1" />
      <location-reach code="2" />
      <location-class code="2" />
      <feature-designation code="PPLC" />
    </location>
    <activity-scope code="8" xml:lang="en">Single Location</activity-scope>
    <default-flow-type code="10">ODA</default-flow-type>
    <default-aid-type code="C01">Project Type Interventions</default-aid-type>
    <collaboration-type code="4">Multilateral outflows</collaboration-type>
    <default-finance-type code="110">Grant</default-finance-type>
    <default-tied-status code="5">Untied</default-tied-status>
  </iati-activity>
  <iati-activity last-updated-datetime="2016-02-01T00:00:00" default-currency="USD" xml:lang="en" hierarchy="1">
    <reporting-org ref="XM-DAC-41114" type="40">United Nations Development Programme</reporting-org>
    <iati-identifier>XM-DAC-41114-PROJECT-00065695</iati-identifier>
    <activity-status code="2">Implementation</activity-status>
    <related-activity type="2" ref="XM-DAC-41114-OUTPUT-00082076" />
    <title>Environment Sustainability and Climate Change</title>
    <description type="1">Strengthening Capacity for Environmental Sustainability and Climate Change.</description>
    <participating-org role="Implementing" type="10" ref="02897">National Execution</participating-org>
    <participating-org role="Accountable" type="10" ref="00012">United Nations Development Programme</participating-org>
    <participating-org role="Funding" type="40" ref="00012">UNITED NATIONS DEVELOPMENT PROGRAMME</participating-org>
    <activity-date type="start-planned" iso-date="2012-03-15">2012-03-15</activity-date>
    <activity-date type="start-actual" iso-date="2012-03-15">2012-03-15</activity-date>
    <activity-date type="end-planned" iso-date="2020-12-31">2020-12-31</activity-date>
    <recipient-country code="SZ">Swaziland</recipient-country>
    <contact-info>
      <email>registry.sz@undp.org</email>
    </contact-info>
    <activity-website>http://www.sz.undp.org/</activity-website>
    <default-flow-type code="10">ODA</default-flow-type>
    <default-aid-type code="C01">Project Type Interventions</default-aid-type>
    <collaboration-type code="4">Multilateral outflows</collaboration-type>
    <default-finance-type code="110">Grant</default-finance-type>
    <default-tied-status code="5">Untied</default-tied-status>
    <conditions attached="0" />
    <document-link format="application/pdf" url="https://info.undp.org/docs/pdc/Documents/SWZ/Project%20document%20for%20the%20Enviromnet%20and%20sustanability%20project.pdf">
      <title>Environment Sustainability &amp; Climate Change Project Document</title>
      <language code="en" />
      <category code="A01" />
      <category code="A02" />
      <category code="A03" />
      <category code="A04" />
      <category code="A05" />
      <category code="A08" />
    </document-link>
    <document-link format="application/pdf" url="http://open.undp.org/#project/00065695">
      <title>Purchase Order Summary</title>
      <language code="en" />
      <category code="A11" />
    </document-link>
    <document-link format="application/pdf" url="http://www.sz.undp.org/content/dam/swaziland/docs/documents/UNDP_SZ_Country_Programme_Action_Plan_2011_2015.pdf">
      <title>UNDP_SZ_Country_Programme_Action_Plan_2011_2015</title>
      <language code="en" />
      <category code="A09" />
    </document-link>
    <document-link format="text/html" url="http://procurement-notices.undp.org/index.cfm">
      <title>Request for Procurement</title>
      <language code="en" />
      <category code="A10" />
    </document-link>
  </iati-activity>
  <iati-activity last-updated-datetime="2016-02-01T00:00:00" default-currency="USD" xml:lang="en" hierarchy="2">
    <reporting-org ref="XM-DAC-41114" type="40">United Nations Development Programme</reporting-org>
    <iati-identifier>XM-DAC-41114-OUTPUT-00082076</iati-identifier>
    <related-activity type="1" ref="XM-DAC-41114-PROJECT-00065695" />
    <recipient-country code="SZ">Swaziland</recipient-country>
    <title xml:lang="en">Env Sustainablty &amp; Clim Change</title>
    <description xml:lang="en" type="1">Improved enabling environment for climate change  and risks integration.</description>
    <activity-date type="start-planned" iso-date="2012-03-15">2012-03-15</activity-date>
    <activity-date type="start-actual" iso-date="2012-03-15">2012-03-15</activity-date>
    <activity-date type="end-planned" iso-date="2015-12-31">2015-12-31</activity-date>
    <sector code="74010" vocabulary="DAC" />
    <sector code="5" vocabulary="RO">Climate Change &amp; Disaster Resilience</sector>
    <country-budget-items vocabulary="1">
      <budget-item code="5.4.11" percentage="100">Social Protection, Land Housing and Community Amenities - disaster prevention and preparedness</budget-item>
    </country-budget-items>
    <participating-org role="Funding" type="40" ref="00012">UNITED NATIONS DEVELOPMENT PROGRAMME</participating-org>
    <budget type="2">
      <period-start iso-date="2016-01-01" />
      <period-end iso-date="2016-12-31" />
      <value currency="USD" value-date="2016-01-31">24435.000</value>
    </budget>
    <budget type="2">
      <period-start iso-date="2015-01-01" />
      <period-end iso-date="2015-12-31" />
      <value currency="USD" value-date="2015-12-31">182625.000</value>
    </budget>
    <budget type="2">
      <period-start iso-date="2014-01-01" />
      <period-end iso-date="2014-12-31" />
      <value currency="USD" value-date="2014-12-31">49715.000</value>
    </budget>
    <budget type="2">
      <period-start iso-date="2013-01-01" />
      <period-end iso-date="2013-12-31" />
      <value currency="USD" value-date="2013-12-31">120320.000</value>
    </budget>
    <budget type="2">
      <period-start iso-date="2012-01-01" />
      <period-end iso-date="2012-12-31" />
      <value currency="USD" value-date="2012-12-31">65570.000</value>
    </budget>
    <transaction>
      <transaction-type code="E">Expenditure</transaction-type>
      <value currency="USD" value-date="2016-01-31">1195.000</value>
      <transaction-date iso-date="2016-01-31" />
      <provider-org ref="41114">United Nations development Programme</provider-org>
      <disbursement-channel code="2">Money is disbursed directly to the implementing institution and managed through a separate bank account</disbursement-channel>
    </transaction>
    <transaction>
      <transaction-type code="C">Commitment</transaction-type>
      <value currency="USD" value-date="2016-01-31">24435.000</value>
      <transaction-date iso-date="2016-01-31" />
      <provider-org ref="00012">UNITED NATIONS DEVELOPMENT PROGRAMME</provider-org>
      <receiver-org ref="41114">United Nations development Programme</receiver-org>
      <disbursement-channel code="2">Money is disbursed directly to the implementing institution and managed through a separate bank account</disbursement-channel>
    </transaction>
    <transaction>
      <transaction-type code="IF">Incoming funds</transaction-type>
      <value currency="USD" value-date="2016-01-31">0.000</value>
      <transaction-date iso-date="2016-01-31" />
      <provider-org ref="00012">UNITED NATIONS DEVELOPMENT PROGRAMME</provider-org>
      <receiver-org ref="41114">United Nations development Programme</receiver-org>
      <disbursement-channel code="2">Money is disbursed directly to the implementing institution and managed through a separate bank account</disbursement-channel>
    </transaction>
    <transaction>
      <transaction-type code="E">Expenditure</transaction-type>
      <value currency="USD" value-date="2015-12-31">182625.000</value>
      <transaction-date iso-date="2015-12-31" />
      <provider-org ref="41114">United Nations development Programme</provider-org>
      <disbursement-channel code="2">Money is disbursed directly to the implementing institution and managed through a separate bank account</disbursement-channel>
    </transaction>
    <transaction>
      <transaction-type code="E">Expenditure</transaction-type>
      <value currency="USD" value-date="2014-12-31">49540.000</value>
      <transaction-date iso-date="2014-12-31" />
      <provider-org ref="41114">United Nations development Programme</provider-org>
      <disbursement-channel code="2">Money is disbursed directly to the implementing institution and managed through a separate bank account</disbursement-channel>
    </transaction>
    <transaction>
      <transaction-type code="E">Expenditure</transaction-type>
      <value currency="USD" value-date="2013-12-31">112272.000</value>
      <transaction-date iso-date="2013-12-31" />
      <provider-org ref="41114">United Nations development Programme</provider-org>
      <disbursement-channel code="2">Money is disbursed directly to the implementing institution and managed through a separate bank account</disbursement-channel>
    </transaction>
    <transaction>
      <transaction-type code="E">Expenditure</transaction-type>
      <value currency="USD" value-date="2012-12-31">65478.000</value>
      <transaction-date iso-date="2012-12-31" />
      <provider-org ref="41114">United Nations development Programme</provider-org>
      <disbursement-channel code="2">Money is disbursed directly to the implementing institution and managed through a separate bank account</disbursement-channel>
    </transaction>
    <policy-marker code="1" vocabulary="DAC" significance="0">Gender Equality</policy-marker>
    <location ref="SZ">
      <location-id vocabulary="G1" code="934841" />
      <name>Kingdom of Swaziland</name>
      <description>independent political entity</description>
      <activity-description></activity-description>
      <administrative level="0" code="934841" vocabulary="G1" />
      <point srsName="http://www.opengis.net/def/crs/EPSG/0/4326">
        <pos>-26.500000 31.500000</pos>
      </point>
      <exactness code="1" />
      <location-reach code="2" />
      <location-class code="1" />
      <feature-designation code="PCLI" />
    </location>
    <activity-scope code="4" xml:lang="en">National</activity-scope>
    <default-flow-type code="10">ODA</default-flow-type>
    <default-aid-type code="C01">Project Type Interventions</default-aid-type>
    <collaboration-type code="4">Multilateral outflows</collaboration-type>
    <default-finance-type code="110">Grant</default-finance-type>
    <default-tied-status code="5">Untied</default-tied-status>
  </iati-activity>
  <iati-activity last-updated-datetime="2016-02-01T00:00:00" default-currency="USD" xml:lang="en" hierarchy="1">
    <reporting-org ref="XM-DAC-41114" type="40">United Nations Development Programme</reporting-org>
    <iati-identifier>XM-DAC-41114-PROJECT-00079928</iati-identifier>
    <activity-status code="2">Implementation</activity-status>
    <related-activity type="2" ref="XM-DAC-41114-OUTPUT-00089803" />
    <title>Climate Smart Agriculture</title>
    <description type="1">Upscaling of climate smart agriculture in Swaziland. This will include piloting of conservation agriculture, water efficient irrigation technologies and high value marketing options.</description>
    <participating-org role="Implementing" type="10" ref="02898">Government of SWAZILAND</participating-org>
    <participating-org role="Accountable" type="10" ref="00012">United Nations Development Programme</participating-org>
    <participating-org role="Funding" type="22" ref="12192">Common Market for Eastern and Southern Africa (COMESA)</participating-org>
    <activity-date type="start-planned" iso-date="2014-03-01">2014-03-01</activity-date>
    <activity-date type="start-actual" iso-date="2014-03-01">2014-03-01</activity-date>
    <activity-date type="end-planned" iso-date="2016-12-31">2016-12-31</activity-date>
    <recipient-country code="SZ">Swaziland</recipient-country>
    <contact-info>
      <email>registry.sz@undp.org</email>
    </contact-info>
    <activity-website>http://www.sz.undp.org/</activity-website>
    <default-flow-type code="10">ODA</default-flow-type>
    <default-aid-type code="C01">Project Type Interventions</default-aid-type>
    <collaboration-type code="4">Multilateral outflows</collaboration-type>
    <default-finance-type code="110">Grant</default-finance-type>
    <default-tied-status code="5">Untied</default-tied-status>
    <conditions attached="0" />
    <document-link format="application/pdf" url="https://info.undp.org/docs/pdc/Documents/SWZ/UNDP%20NAMBoard%20LOA%20Signed.pdf">
      <title>UNDP NAMBoard NIM LOA and Attachments</title>
      <language code="en" />
      <category code="A09" />
    </document-link>
    <document-link format="application/pdf" url="https://info.undp.org/docs/pdc/Documents/SWZ/Sub-Agreement%20with%20COMESA%20signed.pdf">
      <title>UNDP COMESA Agreement Signed</title>
      <language code="en" />
      <category code="A09" />
    </document-link>
    <document-link format="application/pdf" url="https://info.undp.org/docs/pdc/Documents/SWZ/CSA%20Proposal%2010112013.pdf">
      <title>Climate Smart Agriculture Project Document</title>
      <language code="en" />
      <category code="A01" />
      <category code="A02" />
      <category code="A03" />
      <category code="A04" />
      <category code="A05" />
      <category code="A08" />
    </document-link>
    <document-link format="application/pdf" url="https://info.undp.org/docs/pdc/Documents/SWZ/Climate%20Smart%20Agriculture%20%20Baseline%20Study%20NAMBOARD%20FINAL.pdf">
      <title>Baseline Study TORs</title>
      <language code="en" />
      <category code="A10" />
    </document-link>
    <document-link format="application/msword" url="https://info.undp.org/docs/pdc/Documents/SWZ/Smart%20Climate%20Change%20-%20Mpatheni%20Community%20members%20laying%20the%20main%20lines%20from%20dam%20to%20irrigated%20fields.jpg.docx">
      <title>Mpatheni Community members laying the main lines from dam to irrigated fields</title>
      <language code="en" />
    </document-link>
    <document-link format="application/pdf" url="http://open.undp.org/#project/00079928">
      <title>Purchase Order Summary</title>
      <language code="en" />
      <category code="A11" />
    </document-link>
  </iati-activity>
  <iati-activity last-updated-datetime="2016-02-01T00:00:00" default-currency="USD" xml:lang="en" hierarchy="2">
    <reporting-org ref="XM-DAC-41114" type="40">United Nations Development Programme</reporting-org>
    <iati-identifier>XM-DAC-41114-OUTPUT-00089803</iati-identifier>
    <related-activity type="1" ref="XM-DAC-41114-PROJECT-00079928" />
    <recipient-country code="SZ">Swaziland</recipient-country>
    <title xml:lang="en">Climate Smart Agriculture</title>
    <description xml:lang="en" type="1">Pilot programme for Upscaling Conservation Agriculture, Water Efficient Irrigation Technologies and High Value Crops Marketing.</description>
    <activity-date type="start-planned" iso-date="2014-03-01">2014-03-01</activity-date>
    <activity-date type="start-actual" iso-date="2014-03-01">2014-03-01</activity-date>
    <activity-date type="end-planned" iso-date="2015-12-31">2015-12-31</activity-date>
    <sector code="74010" vocabulary="DAC" />
    <sector code="5" vocabulary="RO">Climate Change &amp; Disaster Resilience</sector>
    <country-budget-items vocabulary="1">
      <budget-item code="5.4.11" percentage="100">Social Protection, Land Housing and Community Amenities - disaster prevention and preparedness</budget-item>
    </country-budget-items>
    <participating-org role="Funding" type="22" ref="12192">Common Market for Eastern and Southern Africa (COMESA)</participating-org>
    <budget type="2">
      <period-start iso-date="2016-01-01" />
      <period-end iso-date="2016-12-31" />
      <value currency="USD" value-date="2016-01-31">69970.000</value>
    </budget>
    <budget type="2">
      <period-start iso-date="2015-01-01" />
      <period-end iso-date="2015-12-31" />
      <value currency="USD" value-date="2015-12-31">128755.000</value>
    </budget>
    <budget type="2">
      <period-start iso-date="2014-01-01" />
      <period-end iso-date="2014-12-31" />
      <value currency="USD" value-date="2014-12-31">308415.000</value>
    </budget>
    <transaction>
      <transaction-type code="E">Expenditure</transaction-type>
      <value currency="USD" value-date="2016-01-31">10144.000</value>
      <transaction-date iso-date="2016-01-31" />
      <provider-org ref="41114">United Nations development Programme</provider-org>
      <disbursement-channel code="2">Money is disbursed directly to the implementing institution and managed through a separate bank account</disbursement-channel>
    </transaction>
    <transaction>
      <transaction-type code="C">Commitment</transaction-type>
      <value currency="USD" value-date="2016-01-31">69970.000</value>
      <transaction-date iso-date="2016-01-31" />
      <provider-org ref="12192">Common Market for Eastern and Southern Africa (COMESA)</provider-org>
      <receiver-org ref="41114">United Nations development Programme</receiver-org>
      <disbursement-channel code="2">Money is disbursed directly to the implementing institution and managed through a separate bank account</disbursement-channel>
    </transaction>
    <transaction>
      <transaction-type code="IF">Incoming funds</transaction-type>
      <value currency="USD" value-date="2016-01-31">0.000</value>
      <transaction-date iso-date="2016-01-31" />
      <provider-org ref="12192">Common Market for Eastern and Southern Africa (COMESA)</provider-org>
      <receiver-org ref="41114">United Nations development Programme</receiver-org>
      <disbursement-channel code="2">Money is disbursed directly to the implementing institution and managed through a separate bank account</disbursement-channel>
    </transaction>
    <transaction>
      <transaction-type code="E">Expenditure</transaction-type>
      <value currency="USD" value-date="2015-12-31">67121.000</value>
      <transaction-date iso-date="2015-12-31" />
      <provider-org ref="41114">United Nations development Programme</provider-org>
      <disbursement-channel code="2">Money is disbursed directly to the implementing institution and managed through a separate bank account</disbursement-channel>
    </transaction>
    <transaction>
      <transaction-type code="E">Expenditure</transaction-type>
      <value currency="USD" value-date="2014-12-31">250994.000</value>
      <transaction-date iso-date="2014-12-31" />
      <provider-org ref="41114">United Nations development Programme</provider-org>
      <disbursement-channel code="2">Money is disbursed directly to the implementing institution and managed through a separate bank account</disbursement-channel>
    </transaction>
    <policy-marker code="1" vocabulary="DAC" significance="0">Gender Equality</policy-marker>
    <activity-scope code="4" xml:lang="en">National</activity-scope>
    <default-flow-type code="10">ODA</default-flow-type>
    <default-aid-type code="C01">Project Type Interventions</default-aid-type>
    <collaboration-type code="4">Multilateral outflows</collaboration-type>
    <default-finance-type code="110">Grant</default-finance-type>
    <default-tied-status code="5">Untied</default-tied-status>
  </iati-activity>
  <iati-activity last-updated-datetime="2016-02-01T00:00:00" default-currency="USD" xml:lang="en" hierarchy="1">
    <reporting-org ref="XM-DAC-41114" type="40">United Nations Development Programme</reporting-org>
    <iati-identifier>XM-DAC-41114-PROJECT-00081957</iati-identifier>
    <activity-status code="2">Implementation</activity-status>
    <related-activity type="2" ref="XM-DAC-41114-OUTPUT-00091061" />
    <title>Strengthening National Protected Areas System</title>
    <description type="1">To strengthen the management effectiveness of the Protected Area system of Swaziland to ensure a viable set of representative samples of the country’s full range of natural ecosystems are conserved, through a network of PAs.</description>
    <participating-org role="Implementing" type="10" ref="02898">Government of SWAZILAND</participating-org>
    <participating-org role="Accountable" type="10" ref="00012">United Nations Development Programme</participating-org>
    <participating-org role="Funding" type="40" ref="10003">Global Environment Fund Truste</participating-org>
    <activity-date type="start-planned" iso-date="2014-02-01">2014-02-01</activity-date>
    <activity-date type="start-actual" iso-date="2014-02-01">2014-02-01</activity-date>
    <activity-date type="end-planned" iso-date="2020-02-29">2020-02-29</activity-date>
    <recipient-country code="SZ">Swaziland</recipient-country>
    <contact-info>
      <email>registry.sz@undp.org</email>
    </contact-info>
    <activity-website>http://www.sz.undp.org/</activity-website>
    <default-flow-type code="10">ODA</default-flow-type>
    <default-aid-type code="C01">Project Type Interventions</default-aid-type>
    <collaboration-type code="4">Multilateral outflows</collaboration-type>
    <default-finance-type code="110">Grant</default-finance-type>
    <default-tied-status code="5">Untied</default-tied-status>
    <conditions attached="0" />
    <document-link format="application/pdf" url="https://info.undp.org/docs/pdc/Documents/SWZ/LOA_UNDP_and_SNTC_for%20support%20services%20to%20NIM%20new.pdf">
      <title>LOA UNDP SNTC</title>
      <language code="en" />
      <category code="A09" />
    </document-link>
    <document-link format="application/pdf" url="https://info.undp.org/docs/pdc/Documents/SWZ/4932%20Swaziland%20BGP%20SNTC%20MoU%20Final%20signed%20copy.pdf">
      <title>4932 Swaziland BGP SNTC MoU Final signed copy</title>
      <language code="en" />
      <category code="A09" />
    </document-link>
    <document-link format="application/pdf" url="https://info.undp.org/docs/pdc/Documents/SWZ/Swaziland%20Protected%20Areas%20PRODOC.pdf">
      <title>Swaziland Protected Areas PRODOC</title>
      <language code="en" />
      <category code="A01" />
      <category code="A02" />
      <category code="A03" />
      <category code="A04" />
      <category code="A05" />
      <category code="A08" />
    </document-link>
    <document-link format="application/pdf" url="http://open.undp.org/#project/00081957">
      <title>Purchase Order Summary</title>
      <language code="en" />
      <category code="A11" />
    </document-link>
    <document-link format="text/html" url="http://procurement-notices.undp.org/index.cfm">
      <title>Request for Procurement</title>
      <language code="en" />
      <category code="A10" />
    </document-link>
  </iati-activity>
  <iati-activity last-updated-datetime="2016-02-01T00:00:00" default-currency="USD" xml:lang="en" hierarchy="2">
    <reporting-org ref="XM-DAC-41114" type="40">United Nations Development Programme</reporting-org>
    <iati-identifier>XM-DAC-41114-OUTPUT-00091061</iati-identifier>
    <related-activity type="1" ref="XM-DAC-41114-PROJECT-00081957" />
    <recipient-country code="SZ">Swaziland</recipient-country>
    <title xml:lang="en">Strengthening National PAs</title>
    <description xml:lang="en" type="1">To strengthen the management effectiveness of the Protected Area system of Swaziland to ensure a viable set of representative samples of the country’s full range of natural ecosystems are conserved, through a network of PAs.</description>
    <activity-date type="start-planned" iso-date="2014-02-01">2014-02-01</activity-date>
    <activity-date type="start-actual" iso-date="2014-02-01">2014-02-01</activity-date>
    <activity-date type="end-planned" iso-date="2020-02-29">2020-02-29</activity-date>
    <sector code="74010" vocabulary="DAC" />
    <sector code="5" vocabulary="RO">Climate Change &amp; Disaster Resilience</sector>
    <country-budget-items vocabulary="1">
      <budget-item code="5.4.11" percentage="100">Social Protection, Land Housing and Community Amenities - disaster prevention and preparedness</budget-item>
    </country-budget-items>
    <participating-org role="Funding" type="40" ref="10003">Global Environment Fund Truste</participating-org>
    <budget type="2">
      <period-start iso-date="2016-01-01" />
      <period-end iso-date="2016-12-31" />
      <value currency="USD" value-date="2016-01-31">0.000</value>
    </budget>
    <budget type="2">
      <period-start iso-date="2015-01-01" />
      <period-end iso-date="2015-12-31" />
      <value currency="USD" value-date="2015-12-31">223893.000</value>
    </budget>
    <budget type="2">
      <period-start iso-date="2014-01-01" />
      <period-end iso-date="2014-12-31" />
      <value currency="USD" value-date="2014-12-31">68205.000</value>
    </budget>
    <transaction>
      <transaction-type code="E">Expenditure</transaction-type>
      <value currency="USD" value-date="2016-01-31">83.000</value>
      <transaction-date iso-date="2016-01-31" />
      <provider-org ref="41114">United Nations development Programme</provider-org>
      <disbursement-channel code="2">Money is disbursed directly to the implementing institution and managed through a separate bank account</disbursement-channel>
    </transaction>
    <transaction>
      <transaction-type code="C">Commitment</transaction-type>
      <value currency="USD" value-date="2016-01-31">0.000</value>
      <transaction-date iso-date="2016-01-31" />
      <provider-org ref="10003">Global Environment Fund Truste</provider-org>
      <receiver-org ref="41114">United Nations development Programme</receiver-org>
      <disbursement-channel code="2">Money is disbursed directly to the implementing institution and managed through a separate bank account</disbursement-channel>
    </transaction>
    <transaction>
      <transaction-type code="IF">Incoming funds</transaction-type>
      <value currency="USD" value-date="2016-01-31">0.000</value>
      <transaction-date iso-date="2016-01-31" />
      <provider-org ref="10003">Global Environment Fund Truste</provider-org>
      <receiver-org ref="41114">United Nations development Programme</receiver-org>
      <disbursement-channel code="2">Money is disbursed directly to the implementing institution and managed through a separate bank account</disbursement-channel>
    </transaction>
    <transaction>
      <transaction-type code="E">Expenditure</transaction-type>
      <value currency="USD" value-date="2015-12-31">230495.000</value>
      <transaction-date iso-date="2015-12-31" />
      <provider-org ref="41114">United Nations development Programme</provider-org>
      <disbursement-channel code="2">Money is disbursed directly to the implementing institution and managed through a separate bank account</disbursement-channel>
    </transaction>
    <transaction>
      <transaction-type code="E">Expenditure</transaction-type>
      <value currency="USD" value-date="2014-12-31">66666.000</value>
      <transaction-date iso-date="2014-12-31" />
      <provider-org ref="41114">United Nations development Programme</provider-org>
      <disbursement-channel code="2">Money is disbursed directly to the implementing institution and managed through a separate bank account</disbursement-channel>
    </transaction>
    <policy-marker code="1" vocabulary="DAC" significance="1">Gender Equality</policy-marker>
    <default-flow-type code="10">ODA</default-flow-type>
    <default-aid-type code="C01">Project Type Interventions</default-aid-type>
    <collaboration-type code="4">Multilateral outflows</collaboration-type>
    <default-finance-type code="110">Grant</default-finance-type>
    <default-tied-status code="5">Untied</default-tied-status>
  </iati-activity>
</iati-activities>