{"document_name":[["AWP GASO 2011 firmado-00035230.pdf"],["http://www.undp.org/content/dam/undp/documents/projects/DOM/00033753/AWP GASO 2011 firmado-00035230.pdf"]],"end":"2011-12-31","fiscal_year":["2011"],"inst_descr":"Secretariado Tecnico de la Pre","inst_id":"00932","inst_type_descr":"Gov Counterpart Institution","inst_type_id":"GOV","operating_unit":"Dominican Republic","operating_unit_id":"DOM","outputs":[{"award_id":"00033753","budget":[110000.0],"crs":"15110","crs_descr":"Economic and development policy/planning","donor_budget":[110000.0],"donor_country":["Dominican Republic"],"donor_country_id":["DOM"],"donor_expend":[110280.95],"donor_id":["00098"],"donor_name":["GOVERNMENT OF DOMINICAN REPUBLIC"],"donor_short":["DOM"],"donor_type":["PROGRAMME COUNTRY"],"donor_type_id":["PROGCTY"],"expenditure":[110280.95],"fiscal_year":["2011"],"focus_area":"1","focus_area_descr":"Poverty reduction & MDG achievement","gender_descr":"Some Contribution","gender_id":"GEN1","output_descr":"Fortalecer las capacidades nacionales de monitoreo y seguimiento de las pol\u00edticas sociales para optimizar un seguimiento, coordinaci\u00f3n e implementaci\u00f3n eficiente y efectiva de las pol\u00edticas p\u00fablicas, fortaleciendo la OTS del Gabinete Social","output_id":"00035230","output_title":"Gabinete Social"}],"project_descr":"Apoyo al Fortalecimiento del Gabinete Social del Gobierno Dominicano, Orientado al Cumplimiento de los Objetivos del Milenio","project_id":"00033753","project_title":"Fortalec. Gabinete Social","region_id":"RBLAC","region_name":"Reg Bur Latin Amer & Carib","start":"2004-02-02"}