{
    "description": "The project will work with the National Centre for Infectious Diseases to increase their technical capacities in identifying behavioural patterns within hidden populations and sexual minorities in Libya.  Further, it will work with NCID in establishing w", 
    "end": "2011-04-30 00:00:00", 
    "fiscal_year": "2010", 
    "id": "00057969", 
    "operating_unit": "LBY", 
    "region": "RBAS", 
    "start": "2009-07-19 00:00:00", 
    "subproject": [
        {
            "budget": "34000", 
            "corporate outcome": "1", 
            "crs": "15110", 
            "description": "Capacity development of NCID staff in data gathering techniques to assess behaviour in high risk populations , in statistic techniques", 
            "donor": "UNDP", 
            "end date": "2010-10-31 00:00:00.0", 
            "expenditure": "29289.07", 
            "fiscal year": "2010", 
            "focus area": "1", 
            "gender code": "Some contribution to gender equality", 
            "id": "00071799", 
            "project_id": "00057969", 
            "start date": "2009-07-19 00:00:00.0", 
            "title": "Capacity developm NCID staff i"
        }, 
        {
            "budget": "36000", 
            "corporate outcome": "1", 
            "crs": "15110", 
            "description": "Strengthen NCID role in its work with hidden community , compile working groups of MSM and commercial sex workers", 
            "donor": "UNDP", 
            "end date": "2010-10-31 00:00:00.0", 
            "expenditure": "30583.49", 
            "fiscal year": "2010", 
            "focus area": "1", 
            "gender code": "No noticeable contribution to gender equality", 
            "id": "00071800", 
            "project_id": "00057969", 
            "start date": "2009-07-19 00:00:00.0", 
            "title": "Strengthen NCID role-work with"
        }
    ], 
    "title": "HIV Risk Reduction Among High Risk Populations in Libya"
}