{"document_name":[],"end":"2013-12-31","fiscal_year":["2011","2012"],"inst_descr":"UNITED NATIONS DEVELOPMENT PRO","inst_id":"00229","inst_type_descr":"UNDP","inst_type_id":"UND","operating_unit":"Spcl Unit for South South Coop","operating_unit_id":"H42","outputs":[{"award_id":"00050585","budget":[75457.15,72701.27],"crs":"99810","crs_descr":"Sectors Not Specified","donor_budget":[76743.36,52534.42,18880.64],"donor_country":["Japan","Japan","Japan"],"donor_country_id":["JPN","JPN","JPN"],"donor_expend":[11706.36,28631.14,13845.119999999999],"donor_id":["00141","00455","11140"],"donor_name":["GOVERNMENT OF JAPAN","JAPANESE INTNL COOP  AC.:UNCDF","Japanese international Cooperation Agenc"],"donor_short":["JPN","JICA","SYR-JICA"],"donor_type":["NON_PROGRAMME COUNTRY","NON_PROGRAMME COUNTRY","NON_PROGRAMME COUNTRY"],"donor_type_id":["NON_PROGCTY","NON_PROGCTY","NON_PROGCTY"],"expenditure":[21988.78,32193.84],"fiscal_year":["2012","2011"],"focus_area":"-","focus_area_descr":"-","gender_descr":"No Contribution","gender_id":"GEN0","output_descr":"-","output_id":"00062565","output_title":"Resource Mobilization & Fund M"}],"project_descr":"Resource Mobilization & Fund Management, Ph III","project_id":"00050585","project_title":"Resource Mobilization & Fund Management, Ph III","region_id":"SU_TCDC","region_name":"Spcl Unit for South South Coop","start":"2008-07-31","subnational":[]}