{"project_descr": "Renforcement des Capacit\u00e9s Nationales en Gestion  des Risques et des Catastrophes", "fiscal_year": [2014, 2012, 2013], "end": "2013-12-31", "region_id": "RBAS", "operating_unit_email": "registry.dj@undp.org", "inst_id": "00908", "outputs": [{"output_id": "00082172", "crs": "74010", "donor_id": ["00141"], "focus_area": "5", "gender_descr": "Gender Equality", "output_title": "Gestion des Catastrophes", "budget": [500000.0, 63419.0, 0.0], "fiscal_year": [2012, 2013, 2014], "gender_id": "1", "donor_name": ["GOVERNMENT OF JAPAN"], "award_id": "00065828", "output_descr": "Renforcement des Capacit\u00e9s Nationales en Gestion  des Risques et des Catastrophes", "donor_short": ["JPN"], "expenditure": [436714.0, 61122.0, -4450.0], "crs_descr": null, "focus_area_descr": "Climate Change & Disaster Resilience"}], "subnational": [{"outputID": "00082172", "output_locID": "00082172-1", "name": "Republic of Djibouti", "focus_area": "5", "lat": "11.833330", "type": "PCLI", "awardID": "00065828", "lon": "42.500000", "precision": "1", "focus_area_descr": "Climate Change & Disaster Resilience"}], "operating_unit": "Djibouti", "budget": 563419.0, "iati_op_id": "DJ", "inst_descr": "National Execution", "start": "2012-03-22", "operating_unit_id": "DJI", "expenditure": 493386.0, "document_name": [], "project_id": "00065828", "inst_type_id": "10", "operating_unit_website": "http://www.dj.undp.org/", "project_title": "gestion des catastrophes"}