{"project_descr": "The primary objective of the project is to reduce greenhouse gas (GHG) emissions caused by the electricity consumption of household appliances in South Africa", "fiscal_year": [2014, 2012], "end": "2017-12-31", "region_id": "RBA", "operating_unit_email": "registry.za@undp.org", "inst_id": "02710", "outputs": [{"output_id": "00077334", "crs": "41010", "donor_id": ["10003"], "focus_area": "4", "gender_descr": "Gender Equality", "output_title": "Market Transformation", "budget": [5000.0, 1250400.0], "fiscal_year": [2012, 2014], "gender_id": "1", "donor_name": ["Global Environment Fund Truste"], "award_id": "00061141", "output_descr": "Policy and regulatory framework for labels and standards", "donor_short": ["GEFTrustee"], "expenditure": [2371.0, 148921.0], "crs_descr": "Environmental policy and administrative management", "focus_area_descr": "Environment & sustainable development"}], "subnational": [{"outputID": "00077334", "output_locID": "00077334-1", "name": "South Africa", "focus_area": "4", "lat": "-29", "type": "PCL", "awardID": "00061141", "lon": "24", "precision": "9", "focus_area_descr": "Environment & sustainable development"}], "operating_unit": "South Africa", "budget": 1255400.0, "iati_op_id": "ZA", "inst_descr": "National Execution", "start": "2012-01-01", "operating_unit_id": "ZAF", "expenditure": 151292.0, "document_name": [["PROJECT IDENTIFICATION FORM (PIF)", "UNDP-CPAP%2bSouth%2bAfrica-March%2b14%2b2013-sig"], ["http://www.undp.org/content/dam/undp/documents/projects/ZAF/2-24-09 ID2692  Revised PIF South Africa S-v6L.doc", "http://www.za.undp.org/content/south_africa/en/home/operations/legal_framework/_jcr_content/centerparsys/download_3/file.res/UNDP-CPAP+South+Africa-March+14+2013-sig.pdf"]], "project_id": "00061141", "inst_type_id": "10", "operating_unit_website": "http://www.za.undp.org/", "project_title": "market transformation through energy efficiency standard"}