{"project_descr": "Strengthening the impact of Public Administration Reform in Can Tho province", "fiscal_year": [2016, 2013, 2014, 2015], "end": "2016-12-31", "region_id": "RBAP", "operating_unit_email": "registry.vn@undp.org", "inst_id": "01138", "outputs": [{"output_id": "00084160", "crs": "15112", "donor_id": ["00256", "XM-DAC-41114"], "disbursement": [], "focus_area": "3", "gender_descr": "Gender Equality", "output_title": "PAR in Can Tho", "budget": [66800.0, 322000.0, 288856.0, 212000.0], "fiscal_year": [2016, 2013, 2014, 2015], "gender_id": "1", "expenditure": [69313.0, 268945.0, 266573.0, 208427.0], "award_id": "00069827", "output_descr": "Strengthening the impact of Public Administration Reform in Can Tho province", "donor_short": ["VIE"], "donor_name": ["GOVERNMENT OF VIET NAM", "UNITED NATIONS DEVELOPMENT PROGRAMME"], "crs_descr": null, "focus_area_descr": "Responsive Institutions"}], "subnational": [{"outputID": "00084160", "output_locID": "00084160-1", "name": "C?n Tho", "focus_area": "3", "lat": "10.033330", "type": "PPLA", "awardID": "00069827", "lon": "105.783330", "precision": "1", "focus_area_descr": "Responsive Institutions"}], "operating_unit": "Viet Nam", "budget": 889656.0, "iati_op_id": "VN", "inst_descr": "Can Tho Peoples committee", "start": "2012-11-01", "operating_unit_id": "VNM", "expenditure": 813258.0, "document_name": [["Prodoc  AWP 20122013 Can Tho", "DPO 69827 (PAR in Can Tho)", "27912_One_Plan_-_ENG_without_signature", "Request for Procurement"], ["https://info.undp.org/docs/pdc/Documents/VNM/Prodoc + AWP 2012-2013 Can Tho.pdf", "https://info.undp.org/docs/pdc/Documents/VNM/1. DPO PAR project Can Tho Eng.15.8.12.doc", "http://www.vn.undp.org/content/dam/vietnam/docs/Legalframework/27912_One_Plan_-_ENG_without_signature.pdf", "http://procurement-notices.undp.org/index.cfm"], ["pdf", "doc", "pdf", ""], [0, 0, 7, 10]], "project_id": "00069827", "inst_type_id": "10", "operating_unit_website": null, "project_title": "public administration reform in can tho"}