{"budget":[195317.0],"document_name":[],"end":"2014-05-30","expenditure":[107128.0],"fiscal_year":["2013","2012"],"iati_op_id":"EC","inst_descr":"MINISTERIO DE MEDIO AMBIENTE","inst_id":"01001","inst_type_id":"10","operating_unit":"Ecuador","operating_unit_email":"registry.ec@undp.org","operating_unit_id":"ECU","operating_unit_website":"http://www.pnud.org.ec/","outputs":[{"award_id":"00066333","budget":[178416.0,16901.0],"crs":"99810","crs_descr":"Sectors Not Specified","donor_id":["00012","10003"],"donor_name":["Voluntary Contributions","Global Environment Fund Truste"],"donor_short":["UNDP","GEFTrustee"],"expenditure":[94097.0,13031.0],"fiscal_year":["2013","2012"],"focus_area":"4","focus_area_descr":"Environment & sustainable development","gender_descr":"Gender Equality","gender_id":"1","output_descr":"This project is part of the second generation of Biodiversity Enabling Activities (BD EA) under the GEF. Ecuador has been Party to the Convention on Biological Diversity (CBD) since February 23, 1993. The project addresses the country's need to continue to fulfill its obligations under the CBD, with particular focus on the Convention's Article 6 and the CBD COP Decision X/2. Above all, the project is a significant contribution to Ecuador's  efforts towards implementing the CBD Strategic Plan 2011-2020 at the national level. The project builds on the current status and achievements of Ecuador's  with respect to biodiversity planning and reporting. It aims to integrate Ecuador's obligations under the CBD into its national development and sectorial planning frameworks through a renewed and participative 'biodiversity planning' and strategizing process. This process is expected to produce measurable targets for biodiversity conservation and sustainable use. It will equally ensure that the value of ecosystems' goods and services, as well as the challenges and opportunities for ecosystem-based adaptation and resilience are taken into consideration in the process. The project will achieve its objective through the implementation of three components, whose activities are thoroughly described in the GEF approved proposal for BD EA.","output_id":"00082536","output_title":"National Biodiversity Planning"}],"project_descr":"This project is part of the second generation of Biodiversity Enabling Activities (BD EA) under the GEF. Ecuador has been Party to the Convention on Biological Diversity (CBD) since February 23, 1993.","project_id":"00066333","project_title":"National Biodiversity Planning to Support imp of CBD","region_id":"RBLAC","start":"2012-05-16","subnational":[{"awardID":"00066333","focus_area":"4","focus_area_descr":"Environment & sustainable development","lat":"-2","lon":"-77.5","name":"Ecuador","outputID":"00082536","output_locID":"00082536-1","precision":"9","type":"PCL"}]}