{"budget":[0.0],"document_name":[],"end":"2014-12-31","expenditure":[0.0],"fiscal_year":["2013"],"iati_op_id":"CD","inst_descr":"National Execution","inst_id":"00942","inst_type_id":"10","operating_unit":"Democratic Republic of Congo","operating_unit_email":"registry.cd@undp.com","operating_unit_id":"COD","operating_unit_website":"http://www.cd.undp.org/","outputs":[{"award_id":"00075754","budget":[0.0],"crs":"41010","crs_descr":"Environmental policy and administrative management","donor_id":["10003"],"donor_name":["Global Environment Fund Truste"],"donor_short":["GEFTrustee"],"expenditure":[0.0],"fiscal_year":["2013"],"focus_area":"4","focus_area_descr":"Environment & sustainable development","gender_descr":"Gender Equality","gender_id":"1","output_descr":null,"output_id":"00087497","output_title":"RESILIENCE OF MUANDA'S COMMUNI"}],"project_descr":" ","project_id":"00075754","project_title":"RESILIENCE OF MUANDA'S COMMUNITIES FROM COASTAL EROSION","region_id":"RBA","start":"2013-09-01","subnational":[]}