{"project_descr": " ", "fiscal_year": [2013], "end": "2013-12-31", "region_id": "RBA", "operating_unit_email": "registry.za@undp.org", "inst_id": "99999", "outputs": [{"output_id": "00085668", "crs": "15210", "donor_id": ["00012"], "focus_area": "6", "gender_descr": "Gender Equality", "output_title": "Support to South Africa`s Regi", "budget": [29000.0], "fiscal_year": [2013], "gender_id": "1", "donor_name": ["Voluntary Contributions"], "award_id": "00072611", "output_descr": null, "donor_short": ["UNDP"], "expenditure": [4768.0], "crs_descr": "Security system management and reform", "focus_area_descr": "Crisis Prevention & Recovery"}], "subnational": [{"outputID": "00085668", "output_locID": "00085668-1", "name": "South Africa", "focus_area": "6", "lat": "-29", "type": "PCL", "awardID": "00072611", "lon": "24", "precision": "9", "focus_area_descr": "Crisis Prevention & Recovery"}], "operating_unit": "South Africa", "budget": 29000.0, "iati_op_id": "ZA", "inst_descr": "UNDP", "start": "2013-02-19", "operating_unit_id": "ZAF", "expenditure": 4768.0, "document_name": [], "project_id": "00072611", "inst_type_id": "40", "operating_unit_website": "http://www.undp.org.za/", "project_title": "support to south africa`s regional & global engagement"}