{"project_descr": "Mainstreaming Sustainable Land and Forest Management in Dry Mountain Landscapes of Northeastern Armenia", "fiscal_year": [2015, 2014], "end": "2015-02-28", "region_id": "RBEC", "operating_unit_email": "registry.am@undp.org", "inst_id": "99999", "outputs": [{"output_id": "00087720", "crs": "23010", "donor_id": ["10003"], "focus_area": "1", "gender_descr": "Gender Equality", "output_title": "Mainstreaming Sustain. Land &", "budget": [63438.0, 27886.0], "fiscal_year": [2014, 2015], "gender_id": "1", "donor_name": ["Global Environment Fund Truste"], "award_id": "00076210", "output_descr": "Sustainable land and forest management in the north-eastern Armenia", "donor_short": ["GEFTrustee"], "expenditure": [63434.0, 11777.0], "crs_descr": null, "focus_area_descr": "Inclusive & Sustainable Growth"}], "subnational": [], "operating_unit": "Armenia", "budget": 91324.0, "iati_op_id": "AM", "inst_descr": "UNDP", "start": "2014-03-17", "operating_unit_id": "ARM", "expenditure": 75211.0, "document_name": [], "project_id": "00076210", "inst_type_id": "40", "operating_unit_website": "http://www.undp.am/", "project_title": "ppg: mainstream. sust. land & forest mngment in armenia"}