{"project_descr": "Project Initiation Plan for the Localization of the Sustainable Development Goals (SDGs).", "fiscal_year": [2018], "end": "2018-12-31", "region_id": "RBLAC", "operating_unit_email": "registry.gy@undp.org", "inst_id": "XM-DAC-41114", "outputs": [{"output_id": "00109905", "crs": "41010", "donor_id": ["00012"], "disbursement": [], "focus_area": "2", "gender_descr": "Gender Equality", "output_title": "Enhanced Knowledge of SDGs", "budget": [45785.0], "fiscal_year": [2018], "gender_id": "1", "expenditure": [1593.0], "award_id": "00110698", "output_descr": "1. Production of Audio Visual and Print materials (including flags, pens, folders, bookmarks, posters, brochures) \n2. Procurement of Equipment (tripod, camera, back up cleaning kit, mobile phone, projector, microphone)\n3. Production of Videos on SDGs implementation and success stories to date\n4. Dissemination of educational and awareness materials", "donor_short": ["UNDP"], "donor_name": ["Voluntary Contributions"], "crs_descr": null, "focus_area_descr": "Democratic Governance"}, {"output_id": "00109906", "crs": "41010", "donor_id": ["00012"], "disbursement": [], "focus_area": "2", "gender_descr": "Gender Equality", "output_title": "SDGs Localized", "budget": [103535.0], "fiscal_year": [2018], "gender_id": "1", "expenditure": [1408.0], "award_id": "00110698", "output_descr": "SDGs are incorporated into Region 9 Plan of Action for Regional Development (PARD)", "donor_short": ["UNDP"], "donor_name": ["Voluntary Contributions"], "crs_descr": null, "focus_area_descr": "Democratic Governance"}, {"output_id": "00109907", "crs": "41010", "donor_id": ["00012"], "disbursement": [], "focus_area": "2", "gender_descr": "Gender Equality", "output_title": "TA to Implement SDGs", "budget": [150000.0], "fiscal_year": [2018], "gender_id": "1", "expenditure": [4200.0], "award_id": "00110698", "output_descr": "1. Mainstreaming of SDGs across the following thematic areas: \n-\tConstitutional Reform \n-\tPromotion of Social Cohesion \n-\tGender Parity\n-\tAwareness on NCDs\n-\tPromotion of Human Rights \n-\tPromotion of Business Sector \n-\tSupport for MAPS mission\n-\tSupport for Peace and Development", "donor_short": ["UNDP"], "donor_name": ["Voluntary Contributions"], "crs_descr": null, "focus_area_descr": "Democratic Governance"}], "subnational": [], "operating_unit": "Guyana", "budget": 299320.0, "iati_op_id": "GY", "inst_descr": "United Nations Development Programme", "start": "2018-01-01", "operating_unit_id": "GUY", "expenditure": 7201.0, "document_name": [], "project_id": "00110698", "inst_type_id": "40", "operating_unit_website": null, "project_title": "localization of sdgs"}